Workbook

Sheet Dashboard

Sheet Funnel
A1: Stage | B1: Job_Count | C1: Pct_of_Discovered
A2: Discovered | B2: 209 | C2: 100
A3: Moved to Scoring | B3: 100 | C3: 47.8
A4: APPLY Decision | B4: 64 | C4: 30.6
A5: Proposal Sent | B5: 25 | C5: 12

Sheet Keyword
A1: Keyword_Search | B1: Tool_Focus | C1: Priority_Score | D1: Status | E1: Total_Scored | F1: APPLY_Count | G1: SKIP_Count | H1: HOLD_Count | I1: APPLY_Rate_Pct | J1: Avg_Score | K1: Avg_Competition | L1: Connect_Efficiency
A2: Power BI Sales Dashboard | B2: Power BI | C2: 0.55 | D2: Test More | E2: 3 | F2: 2 | G2: 1 | H2: 0 | I2: 66.7 | J2: 0.8 | K2: 25 | L2: 0.056140351 | Q2: Keyword | R2: Avg_Competition | S2: Avg_Score | T2: Status | V2: Test_More_X | W2: Test_More_Y | X2: Drop_X | Y2: Drop_Y
A3: Looker Studio Marketing Dashboard | B3: Looker Studio | C3: 0.53 | D3: Test More | E3: 1 | F3: 1 | G3: 0 | H3: 0 | I3: 100 | J3: 0.87 | K3: 15 | L3: 0.048945783 | Q3: =A2 -> Power BI Sales Dashboard | R3: =K2 -> 25 | S3: =J2 -> 0.8 | T3: =D2 -> Test More | V3: =IF(T3="Test More",R3,NA()) -> 25 | W3: =IF(T3="Test More",S3,NA()) -> 0.8 | X3: =IF(T3="Drop",R3,NA()) -> #N/A | Y3: =IF(T3="Drop",S3,NA()) -> #N/A
A4: looker studio marketing dashboard | B4: Looker Studio | C4: 0.53 | D4: Test More | E4: 3 | F4: 1 | G4: 2 | H4: 0 | I4: 33.3 | J4: 0.793 | K4: 13 | L4: 0.048945783 | N4: =INDEX(Keyword!A2:A21,MATCH(MAX(Keyword!C2:C21),Keyword!C2:C21,0)) -> Power BI Sales Dashboard | Q4: =A3 -> Looker Studio Marketing Dashboard | R4: =K3 -> 15 | S4: =J3 -> 0.87 | T4: =D3 -> Test More | V4: =IF(T4="Test More",R4,NA()) -> 15 | W4: =IF(T4="Test More",S4,NA()) -> 0.87 | X4: =IF(T4="Drop",R4,NA()) -> #N/A | Y4: =IF(T4="Drop",S4,NA()) -> #N/A
A5: Looker Studio Marketing Dashboard Developer | B5: Looker Studio | C5: 0.53 | D5: Test More | E5: 9 | F5: 8 | G5: 1 | H5: 0 | I5: 88.9 | J5: 0.74 | K5: 13.9 | L5: 0.052282609 | N5: =AVERAGE(Keyword!J2:J21) -> 0.7321 | Q5: =A4 -> looker studio marketing dashboard | R5: =K4 -> 13 | S5: =J4 -> 0.793 | T5: =D4 -> Test More | V5: =IF(T5="Test More",R5,NA()) -> 13 | W5: =IF(T5="Test More",S5,NA()) -> 0.793 | X5: =IF(T5="Drop",R5,NA()) -> #N/A | Y5: =IF(T5="Drop",S5,NA()) -> #N/A
A6: Google Sheets Sales Dashboard | B6: Other | C6: 0.49 | D6: Test More | E6: 1 | F6: 1 | G6: 0 | H6: 0 | I6: 100 | J6: 0.81 | K6: 5 | L6: 0.070434783 | Q6: =A5 -> Looker Studio Marketing Dashboard Developer | R6: =K5 -> 13.9 | S6: =J5 -> 0.74 | T6: =D5 -> Test More | V6: =IF(T6="Test More",R6,NA()) -> 13.9 | W6: =IF(T6="Test More",S6,NA()) -> 0.74 | X6: =IF(T6="Drop",R6,NA()) -> #N/A | Y6: =IF(T6="Drop",S6,NA()) -> #N/A
A7: Power BI Operations Dashboard | B7: Power BI | C7: 0.48 | D7: Test More | E7: 6 | F7: 4 | G7: 2 | H7: 0 | I7: 66.7 | J7: 0.717 | K7: 35 | L7: 0.056578947 | N7: =INDEX(Keyword!A2:A21,MATCH(MAX(Keyword!L2:L21),Keyword!L2:L21,0)) -> Google Sheets Sales Dashboard | Q7: =A6 -> Google Sheets Sales Dashboard | R7: =K6 -> 5 | S7: =J6 -> 0.81 | T7: =D6 -> Test More | V7: =IF(T7="Test More",R7,NA()) -> 5 | W7: =IF(T7="Test More",S7,NA()) -> 0.81 | X7: =IF(T7="Drop",R7,NA()) -> #N/A | Y7: =IF(T7="Drop",S7,NA()) -> #N/A
A8: tableau dashboard | B8: Tableau | C8: 0.47 | D8: Test More | E8: 10 | F8: 7 | G8: 2 | H8: 1 | I8: 70 | J8: 0.711 | K8: 30 | L8: 0.053959821 | N8: =AVERAGE(Keyword!L2:L21) -> 0.055747606 | Q8: =A7 -> Power BI Operations Dashboard | R8: =K7 -> 35 | S8: =J7 -> 0.717 | T8: =D7 -> Test More | V8: =IF(T8="Test More",R8,NA()) -> 35 | W8: =IF(T8="Test More",S8,NA()) -> 0.717 | X8: =IF(T8="Drop",R8,NA()) -> #N/A | Y8: =IF(T8="Drop",S8,NA()) -> #N/A
A9: SQL Inventory Reporting Dashboard | B9: SQL | C9: 0.47 | D9: Test More | E9: 5 | F9: 4 | G9: 0 | H9: 1 | I9: 80 | J9: 0.676 | K9: 28 | L9: 0.064380952 | Q9: =A8 -> tableau dashboard | R9: =K8 -> 30 | S9: =J8 -> 0.711 | T9: =D8 -> Test More | V9: =IF(T9="Test More",R9,NA()) -> 30 | W9: =IF(T9="Test More",S9,NA()) -> 0.711 | X9: =IF(T9="Drop",R9,NA()) -> #N/A | Y9: =IF(T9="Drop",S9,NA()) -> #N/A
A10: Excel HR Dashboard | B10: Excel | C10: 0.45 | D10: Test More | E10: 1 | F10: 1 | G10: 0 | H10: 0 | I10: 100 | J10: 0.75 | K10: 15 | L10: 0.068181818 | Q10: =A9 -> SQL Inventory Reporting Dashboard | R10: =K9 -> 28 | S10: =J9 -> 0.676 | T10: =D9 -> Test More | V10: =IF(T10="Test More",R10,NA()) -> 28 | W10: =IF(T10="Test More",S10,NA()) -> 0.676 | X10: =IF(T10="Drop",R10,NA()) -> #N/A | Y10: =IF(T10="Drop",S10,NA()) -> #N/A
A11: power bi dashboard | B11: Power BI | C11: 0.44 | D11: Test More | E11: 7 | F11: 6 | G11: 1 | H11: 0 | I11: 85.7 | J11: 0.719 | K11: 29.1 | L11: 0.049073171 | Q11: =A10 -> Excel HR Dashboard | R11: =K10 -> 15 | S11: =J10 -> 0.75 | T11: =D10 -> Test More | V11: =IF(T11="Test More",R11,NA()) -> 15 | W11: =IF(T11="Test More",S11,NA()) -> 0.75 | X11: =IF(T11="Drop",R11,NA()) -> #N/A | Y11: =IF(T11="Drop",S11,NA()) -> #N/A
A12: Excel Finance Dashboard Creation | B12: Excel | C12: 0.44 | D12: Test More | E12: 11 | F12: 6 | G12: 2 | H12: 3 | I12: 54.5 | J12: 0.683 | K12: 34.5 | L12: 0.048159185 | Q12: =A11 -> power bi dashboard | R12: =K11 -> 29.1 | S12: =J11 -> 0.719 | T12: =D11 -> Test More | V12: =IF(T12="Test More",R12,NA()) -> 29.1 | W12: =IF(T12="Test More",S12,NA()) -> 0.719 | X12: =IF(T12="Drop",R12,NA()) -> #N/A | Y12: =IF(T12="Drop",S12,NA()) -> #N/A
A13: Google Sheets Revenue Dashboard | B13: Other | C13: 0.42 | D13: Test More | E13: 2 | F13: 2 | G13: 0 | H13: 0 | I13: 100 | J13: 0.73 | K13: 12.5 | L13: 0.06952381 | Q13: =A12 -> Excel Finance Dashboard Creation | R13: =K12 -> 34.5 | S13: =J12 -> 0.683 | T13: =D12 -> Test More | V13: =IF(T13="Test More",R13,NA()) -> 34.5 | W13: =IF(T13="Test More",S13,NA()) -> 0.683 | X13: =IF(T13="Drop",R13,NA()) -> #N/A | Y13: =IF(T13="Drop",S13,NA()) -> #N/A
A14: Dashboard Customer Service KPI | B14: Other | C14: 0.42 | D14: Test More | E14: 4 | F14: 2 | G14: 2 | H14: 0 | I14: 50 | J14: 0.698 | K14: 33.8 | L14: 0.053653846 | Q14: =A13 -> Google Sheets Revenue Dashboard | R14: =K13 -> 12.5 | S14: =J13 -> 0.73 | T14: =D13 -> Test More | V14: =IF(T14="Test More",R14,NA()) -> 12.5 | W14: =IF(T14="Test More",S14,NA()) -> 0.73 | X14: =IF(T14="Drop",R14,NA()) -> #N/A | Y14: =IF(T14="Drop",S14,NA()) -> #N/A
A15: R Studio Marketing Dashboard | B15: Other | C15: 0.42 | D15: Test More | E15: 2 | F15: 1 | G15: 1 | H15: 0 | I15: 50 | J15: 0.685 | K15: 15 | L15: 0.05372549 | Q15: =A14 -> Dashboard Customer Service KPI | R15: =K14 -> 33.8 | S15: =J14 -> 0.698 | T15: =D14 -> Test More | V15: =IF(T15="Test More",R15,NA()) -> 33.8 | W15: =IF(T15="Test More",S15,NA()) -> 0.698 | X15: =IF(T15="Drop",R15,NA()) -> #N/A | Y15: =IF(T15="Drop",S15,NA()) -> #N/A
A16: business dashboard | B16: Other | C16: 0.4 | D16: Test More | E16: 4 | F16: 2 | G16: 2 | H16: 0 | I16: 50 | J16: 0.72 | K16: 40 | L16: 0.047058824 | Q16: =A15 -> R Studio Marketing Dashboard | R16: =K15 -> 15 | S16: =J15 -> 0.685 | T16: =D15 -> Test More | V16: =IF(T16="Test More",R16,NA()) -> 15 | W16: =IF(T16="Test More",S16,NA()) -> 0.685 | X16: =IF(T16="Drop",R16,NA()) -> #N/A | Y16: =IF(T16="Drop",S16,NA()) -> #N/A
A17: excel dashboard | B17: Excel | C17: 0.38 | D17: Drop | E17: 6 | F17: 3 | G17: 0 | H17: 3 | I17: 50 | J17: 0.638 | K17: 35.8 | L17: 0.053641457 | Q17: =A16 -> business dashboard | R17: =K16 -> 40 | S17: =J16 -> 0.72 | T17: =D16 -> Test More | V17: =IF(T17="Test More",R17,NA()) -> 40 | W17: =IF(T17="Test More",S17,NA()) -> 0.72 | X17: =IF(T17="Drop",R17,NA()) -> #N/A | Y17: =IF(T17="Drop",S17,NA()) -> #N/A
A18: looker studio dashboard | B18: Looker Studio | C18: 0.37 | D18: Drop | E18: 8 | F18: 2 | G18: 6 | H18: 0 | I18: 25 | J18: 0.722 | K18: 34.4 | L18: 0.04515625 | Q18: =A17 -> excel dashboard | R18: =K17 -> 35.8 | S18: =J17 -> 0.638 | T18: =D17 -> Drop | V18: =IF(T18="Test More",R18,NA()) -> #N/A | W18: =IF(T18="Test More",S18,NA()) -> #N/A | X18: =IF(T18="Drop",R18,NA()) -> 35.8 | Y18: =IF(T18="Drop",S18,NA()) -> 0.638
A19: analytics dashboard | B19: Other | C19: 0.32 | D19: Drop | E19: 1 | F19: 1 | G19: 0 | H19: 0 | I19: 100 | J19: 0.67 | K19: 10 | L19: 0.053174603 | Q19: =A18 -> looker studio dashboard | R19: =K18 -> 34.4 | S19: =J18 -> 0.722 | T19: =D18 -> Drop | V19: =IF(T19="Test More",R19,NA()) -> #N/A | W19: =IF(T19="Test More",S19,NA()) -> #N/A | X19: =IF(T19="Drop",R19,NA()) -> 34.4 | Y19: =IF(T19="Drop",S19,NA()) -> 0.722
A20: reporting dashboard | B20: Other | C20: 0.3 | D20: Drop | E20: 1 | F20: 0 | G20: 1 | H20: 0 | I20: 0 | J20: 0.8 | K20: 5 | L20: 0.058823529 | Q20: =A19 -> analytics dashboard | R20: =K19 -> 10 | S20: =J19 -> 0.67 | T20: =D19 -> Drop | V20: =IF(T20="Test More",R20,NA()) -> #N/A | W20: =IF(T20="Test More",S20,NA()) -> #N/A | X20: =IF(T20="Drop",R20,NA()) -> 10 | Y20: =IF(T20="Drop",S20,NA()) -> 0.67
A21: Google Sheets HR Dashboard | B21: Other | C21: 0.28 | D21: Drop | E21: 1 | F21: 0 | G21: 1 | H21: 0 | I21: 0 | J21: 0.71 | K21: 40 | L21: 0.063111111 | Q21: =A20 -> reporting dashboard | R21: =K20 -> 5 | S21: =J20 -> 0.8 | T21: =D20 -> Drop | V21: =IF(T21="Test More",R21,NA()) -> #N/A | W21: =IF(T21="Test More",S21,NA()) -> #N/A | X21: =IF(T21="Drop",R21,NA()) -> 5 | Y21: =IF(T21="Drop",S21,NA()) -> 0.8
Q22: =A21 -> Google Sheets HR Dashboard | R22: =K21 -> 40 | S22: =J21 -> 0.71 | T22: =D21 -> Drop | V22: =IF(T22="Test More",R22,NA()) -> #N/A | W22: =IF(T22="Test More",S22,NA()) -> #N/A | X22: =IF(T22="Drop",R22,NA()) -> 40 | Y22: =IF(T22="Drop",S22,NA()) -> 0.71

Sheet Tools
A1: Tool_Detected | B1: Total_Jobs | C1: Market_Share_Pct | D1: Moved_to_Scoring | E1: Scoring_Rate_Pct
A2: Looker Studio | B2: 43 | C2: 20.6 | D2: 35 | E2: 81.4
A3: Other | B3: 41 | C3: 19.6 | D3: 0 | E3: 0
A4: Excel | B4: 39 | C4: 18.7 | D4: 30 | E4: 76.9
A5: Power BI | B5: 39 | C5: 18.7 | D5: 29 | E5: 74.4
A6: Google Sheets | B6: 32 | C6: 15.3 | D6: 0 | E6: 0
A7: Tableau | B7: 9 | C7: 4.3 | D7: 6 | E7: 66.7
A8: SQL | B8: 6 | C8: 2.9 | D8: 0 | E8: 0

Sheet Scores
A1: Score_Band | B1: Job_Count | C1: Pct_of_Scored | D1: APPLY_Count | E1: SKIP_Count
A2: 1. 0.80+ High | B2: 13 | C2: 13 | D2: 5 | E2: 8
A3: 2. 0.75-0.79 Good | B3: 16 | C3: 16 | D3: 12 | E3: 2
A4: 3. 0.70-0.74 Solid | B4: 27 | C4: 27 | D4: 14 | E4: 11
A5: 4. 0.65-0.69 Marginal | B5: 33 | C5: 33 | D5: 24 | E5: 5
A6: 5. Below 0.65 | B6: 11 | C6: 11 | D6: 9 | E6: 0
A7: AVG_SCORE | D7: 0.71

Sheet Sessions
A1: Session_ID | B1: Date | C1: Duration | D1: Jobs_Logged | E1: Jobs_Moved_To_Scoring | F1: Jobs_Review_Later | G1: Session_Yield | H1: Saturation_Flag | I1: Proposals_Sent | J1: Connects_Spent
A2: S008 | B2: 46112 | C2: 39m 51s | D2: 0 | E2: 8 | F2: 0 | G2: 0 | H2: Saturating | I2: 0 | J2: 0 | K2: =COUNTA(A2:A100) -> 10
A3: S009 | B3: 46113 | C3: 39m 23s | D3: 8 | E3: 6 | F3: 2 | G3: 8 | H3: Healthy | I3: 0 | J3: 0 | K3: =AVERAGE(G2:G11) -> 7.2
A4: S010 | B4: 46115 | C4: 53m 35s | D4: 8 | E4: 6 | F4: 2 | G4: 8 | H4: Healthy | I4: 0 | J4: 0 | K4: =AVERAGE(I2:I11) -> 0.5
A5: S011 | B5: 46116 | C5: 46m 40s | D5: 8 | E5: 6 | F5: 2 | G5: 8 | H5: Healthy | I5: 0 | J5: 0 | K5: =AVERAGE(J2:J11) -> 8.2
A6: S012 | B6: 46118 | C6: 36m 50s | D6: 8 | E6: 5 | F6: 3 | G6: 8 | H6: Healthy | I6: 0 | J6: 0
A7: S013 | B7: 46119 | C7: 12h 48m 41s | D7: 8 | E7: 4 | F7: 4 | G7: 8 | H7: Healthy | I7: 0 | J7: 0
A8: S014 | B8: 46120 | C8: 1h 29m 38s | D8: 8 | E8: 7 | F8: 1 | G8: 8 | H8: Healthy | I8: 1 | J8: 15
A9: S015 | B9: 46120 | C9: 43m 15s | D9: 8 | E9: 3 | F9: 5 | G9: 8 | H9: Healthy | I9: 1 | J9: 21
A10: S016 | B10: 46124 | C10: 19h 5m 50s | D10: 8 | E10: 5 | F10: 3 | G10: 8 | H10: Healthy | I10: 1 | J10: 20
A11: S017 | B11: 46125 | C11: 41m 54s | D11: 8 | E11: 7 | F11: 1 | G11: 8 | H11: Healthy | I11: 2 | J11: 26

Sheet Proposals
A1: Template_Used | B1: Hook_Version | C1: CTA_Version | D1: Proposals_Sent | E1: Avg_Connects | F1: Replies | G1: Interviews | H1: Hires | I1: Reply_Rate_Pct | J1: Interview_Rate_Pct | K1: Hire_Rate_Pct
A2: OVERALL | D2: 26 | E2: 11.3 | F2: 1 | G2: 1 | H2: 1 | I2: 3.8 | J2: 3.8 | K2: 3.8 | M2: =INDEX(Proposals!A3:A5,MATCH(MAX(Proposals!J3:J5),Proposals!J3:J5,0)) -> T1
A3: T1 | B3: A | C3: A | D3: 12 | E3: 12.2 | F3: 1 | G3: 1 | H3: 1 | I3: 8.3 | J3: 8.3 | K3: 8.3
A4: T2 | B4: B | C4: A | D4: 7 | E4: 10 | F4: 0 | G4: 0 | H4: 0 | I4: 0 | J4: 0 | K4: 0
A5: T3 | B5: C | C5: B | D5: 7 | E5: 11.1 | F5: 0 | G5: 0 | H5: 0 | I5: 0 | J5: 0 | K5: 0
A9: Template_Used | B9: Hook_Version | C9: CTA_Version | D9: Reply_Rate_Pct
A10: T1 | B10: A | C10: A | D10: 8.3
A11: T2 | B11: B | C11: A | D11: 0
A12: T3 | B12: C | C12: B | D12: 0

Sheet Complexity
A1: Complexity | B1: Job_Count | C1: Pct_of_Total
A2: Large | B2: 93 | C2: 44.5 | E2: =INDEX(Complexity!A2:A5,MATCH(MAX(Complexity!C2:C5),Complexity!C2:C5,0)) -> Large
A3: Normal | B3: 56 | C3: 26.8 | E3: =INDEX(Complexity!C2:C5,MATCH(MAX(Complexity!C2:C5),Complexity!C2:C5,0)) -> 44.5
A4: Complex | B4: 50 | C4: 23.9
A5: Simple | B5: 10 | C5: 4.8

Sheet Costs
A1: Metric | B1: Value
A2: Cost_per_Connect | B2: 0.15 | D2: Projected | E2: =B36 -> 293
A3: Connect_Replenishment | B3: 283 | D3: Target | E3: =B7 -> 300
A4: Total_Connects_Purchased | B4: 283
A5: Connect_Replenishment_Date | B5: 46116
A6: Connect_Replenishment_Cost | B6: 0
A7: Monthly_Connect_Target | B7: 300
A8: Projected_Monthly_Connect_Use | B8: 293
A9: Projected_Monthly_Replenishment_Connects | B9: 212
A10: Projected_Monthly_Replenishment_Cost | B10: 31.8
A11: Daily_Connect_Budget | B11: 10
A12: Weekly_Connect_Budget | B12: 50
A13: Total_Proposals_Sent | B13: 26
A14: Total_Connects_Used | B14: 295
A15: Total_Proposal_Cost | B15: 44.25
... A37: Projected_Month_End_Cost | B37: 43.95
A38: On_Track_Flag | B38: On Track
A39: Monthly_ROI_Dollar | B39: 127.88
A40: Expected_Value_per_Proposal | B40: 5.77
A41: Revenue_per_Connect | B41: 0.51
A42: Net_Value_per_Connect | B42: 0.36
